LICENSE
README.md
setup.cfg
setup.py
connectNvironment/__init__.py
connectNvironment/connect_n.py
connectNvironment.egg-info/PKG-INFO
connectNvironment.egg-info/SOURCES.txt
connectNvironment.egg-info/dependency_links.txt
connectNvironment.egg-info/requires.txt
connectNvironment.egg-info/top_level.txt